{
  "meals": [
    {
      "name": "chilli_garlic_oil_pasta",
      "ingredients": ["pasta", "chilli", "garlic", "olive_oil"],
      "effort": false,
      "frequency": 2,
      "last_used": "2020-01-01"
    },
    {
      "name": "creamy_mushroom_pasta",
      "ingredients": [
        "pasta",
        "mushroom",
        "double_cream",
        "garlic",
        "parmesan"
      ],
      "effort": false,
      "frequency": 2,
      "last_used": "2020-01-01"
    },
    {
      "name": "halloumi_naan_bread",
      "ingredients": [
        "naan_bread",
        "halloumi",
        "humous",
        "pickled_cabbage",
        "tomato",
        "cucumber"
      ],
      "effort": true,
      "frequency": 2,
      "last_used": "2020-01-01"
    },
    {
      "name": "oven_pizza",
      "ingredients": ["oven_pizza"],
      "effort": false,
      "frequency": 2,
      "last_used": "2020-01-01"
    },
    {
      "name": "spaghetti_bolognese",
      "ingredients": [
        "spaghetti",
        "minced_beef",
        "carrot",
        "celery",
        "red_onion"
      ],
      "effort": true,
      "frequency": 2,
      "last_used": "2020-01-01"
    },
    {
      "name": "paella",
      "ingredients": [
        "paella_rice",
        "white_wine",
        "vegetable_stock",
        "red_pepper",
        "prawns",
        "chorizo",
        "paprika",
        "white_onion"
      ],
      "effort": false,
      "frequency": 2,
      "last_used": "2020-01-01"
    },
    {
      "name": "chilli",
      "ingredients": [
        "beans_in_chilli_sauce",
        "basmati_rice",
        "tinned_tomatoes",
        "minced_beef",
        "carrot",
        "celery",
        "cheddar_cheese"
      ],
      "effort": true,
      "frequency": 2,
      "last_used": "2020-01-01"
    },
    {
      "name": "creamy_borccoli_risotto",
      "ingredients": [
        "vegetable_stock",
        "broccoli",
        "white_onion",
        "risotto_rice",
        "parsley",
        "lemon",
        "gorgonzola"
      ],
      "effort": false,
      "frequency": 5,
      "last_used": "2020-01-01"
    },
    {
      "name": "cauliflower_chickpea_curry",
      "ingredients": [
        "cauliflower",
        "curry_paste",
        "self_raising_flower",
        "chickpeas",
        "coconut_milk",
        "tomato",
        "mango_chutney",
        "naan_bread"
      ],
      "effort": false,
      "frequency": 4,
      "last_used": "2020-01-01"
    },
    {
      "name": "cauliflower_risotto",
      "ingredients": [
          "white_onion",
          "cauliflower",
          "thyme",
          "vegetable_stock",
          "risotto_rice",
          "parmesan",
          "prosciutto"
      ],
      "effort": false,
      "frequency": 3,
      "last_used": "2020-01-01"
    },
    {
      "name": "tarts",
      "ingredients": [
          "puff_pastry",
          "red_onion",
          "goats_cheese",
          "red_pepper",
          "courgette",
          "mozzarella",
          "pesto",
          "salad"
      ],
      "effort": false,
      "frequency": 3,
      "last_used": "2020-01-01"
    },
    {
      "name": "jerk_chicken_burger",
      "ingredients": [
          "red_chilli",
          "chicken_breast",
          "jerk_seasoning",
          "tinned_pineapple_rings",
          "carrot",
          "white_cabbage",
          "natural_yoghurt",
          "brioche_buns"
      ],
      "effort": false,
      "frequency": 5,
      "last_used": "2020-01-01"
    },
    {
      "name": "halloumi_burgers",
      "ingredients": [
          "halloumi",
          "aubergine",
          "red_pepper",
          "mayonaise",
          "harissa_paste",
          "sweet_potato",
          "brioche_buns"
      ],
      "effort": false,
      "frequency": 2,
      "last_used": "2020-01-01"
    },
    {
      "name": "salmon_tacos",
      "ingredients": [
          "tomato",
          "mango",
          "avocado",
          "spring_onion",
          "salmon",
          "cajun_seasoning",
          "tortillas",
          "limes"
      ],
      "effort": true,
      "frequency": 2,
      "last_used": "2020-01-01"
    },
    {
      "name": "sausage_and_mash",
      "ingredients": [
        "sausage",
        "potato",
        "broccoli",
        "red_onion",
        "vegetable_stock"
      ],
      "effort": true,
      "frequency": 6,
      "last_used": "2020-01-01"
    },
    {
      "name": "stuffed_peppers",
      "ingredients": [
        "red_pepper",
        "spicy_rice",
        "olives",
        "feta",
        "salad"
      ],
      "effort": false,
      "frequency": 4,
      "last_used": "2020-01-01"
    },
    {
      "name": "stuffed_mushrooms",
      "ingredients": [
        "mushroom",
        "ricotta",
        "chilli",
        "oregano",
        "lemon",
        "salad"
      ],
      "effort": true,
      "frequency": 4,
      "last_used": "2020-01-01"
    },
    {
      "name": "greek_salad_pasta",
      "ingredients": [
        "pasta",
        "olives",
        "cucumber",
        "feta",
        "tomato"
      ],
      "effort": false,
      "frequency": 2,
      "last_used": "2020-01-01"
    },
    {
      "name": "mushroom_cannelloni",
      "ingredients": [
        "cannelloni",
        "white_onion",
        "garlic",
        "leek",
        "mushroom",
        "plain_flour",
        "milk",
        "cheddar_cheese"
      ],
      "effort": true,
      "frequency": 6,
      "last_used": "2020-01-01"
    },
    {
      "name": "mushroom_cacio_pepe",
      "ingredients": [
        "spaghetti",
        "parmesan",
        "mushroom",
        "truffle_oil",
        "lemon"
      ],
      "effort": false,
      "frequency": 4,
      "last_used": "2020-01-01"
    },
    {
      "name": "lentil_sweet_potato_curry",
      "ingredients": [
        "red_onion",
        "cumin_seeds",
        "mustard_seeds",
        "curry_powder",
        "lentils",
        "sweet_potato",
        "vegetable_stock",
        "tinned_tomatoes",
        "chickpeas",
        "corriander",
        "natural_yoghurt",
        "naan_bread"
      ],
      "effort": true,
      "frequency": 5,
      "last_used": "2020-01-01"
    },
    {
      "name": "spicy_cauliflower_pasta",
      "ingredients": [
        "cauliflower",
        "pasta",
        "garlic",
        "chilli",
        "pine_nuts",
        "lemon",
        "parsley",
        "parmesan"
      ],
      "effort": false,
      "frequency": 3,
      "last_used": "2020-01-01"
    },
    {
      "name": "leek_mushroom_risotto",
      "ingredients": [
        "leek",
        "garlic",
        "risotto_rice",
        "vegetable_stock",
        "mushroom",
        "parmesan"
      ],
      "effort": true,
      "frequency": 5,
      "last_used": "2020-01-01"
    },
    {
      "name": "tomato_basil_mozzarella_pasta",
      "ingredients": [
        "pasta",
        "tomato",
        "mozzarella",
        "basil"
      ],
      "effort": false,
      "frequency": 4,
      "last_used": "2020-01-01"
    },
    {
      "name": "mushroom_risotto",
      "ingredients": [
        "risotto_rice",
        "vegetable_stock",
        "mushroom",
        "dried_mushrooms",
        "parmesan"
      ],
      "effort": true,
      "frequency": 4,
      "last_used": "2020-01-01"
    },
    {
      "name": "sunshine_pasta",
      "ingredients": [
        "pasta",
        "white_onion",
        "garlic",
        "white_wine_vinegar",
        "yellow_pepper",
        "pistachio",
        "parmesan"
      ],
      "effort": true,
      "frequency": 5,
      "last_used": "2020-01-01"
    },
    {
      "name": "courgette_bow_ties",
      "ingredients": [
        "farfalle",
        "garlic",
        "chilli",
        "fennel_seeds",
        "courgette",
        "single_cream",
        "parmesan"
      ],
      "effort": true,
      "frequency": 4,
      "last_used": "2020-01-01"
    },
    {
      "name": "chickpea_chorizo_stew",
      "ingredients": [
        "tinned_tomatoes",
        "chorizo",
        "red_onion",
        "red_pepper",
        "garlic",
        "paprika",
        "chickpeas",
        "rice"
      ],
      "effort": true,
      "frequency": 4,
      "last_used": "2020-01-01"
    },
    {
      "name": "cougette_prawn_orzo",
      "ingredients": [
        "courgette",
        "orzo",
        "white_onion",
        "vegetable_stock",
        "garlic",
        "prawns",
        "paprika",
        "lemon",
        "parsley"
      ],
      "effort": true,
      "frequency": 4,
      "last_used": "2020-01-01"
    },
    {
      "name": "ratatouille_risotto",
      "ingredients": [
        "aubergine",
        "oregano",
        "vegetable_stock",
        "tomato",
        "white_onion",
        "cheddar_cheese",
        "tomato_puree",
        "courgette",
        "yellow_pepper",
        "garlic",
        "basil",
        "risotto_rice"
      ],
      "effort": true,
      "frequency": 5,
      "last_used": "2020-01-01"
    },
    {
      "name": "sairs_spicy_rice",
      "ingredients": [
        "spicy_rice",
        "red_pepper",
        "chorizo",
        "courgette",
        "sweetcorn",
        "paprika"
      ],
      "effort": false,
      "frequency": 3,
      "last_used": "2020-01-01"
    },
    {
      "name": "curry_in_a_hurry",
      "ingredients": [
        "pilau_rice",
        "curry_powder",
        "spinach",
        "red_pepper",
        "courgette",
        "lime",
        "mango_chutney"
      ],
      "effort": false,
      "frequency": 4,
      "last_used": "2020-01-01"
    }
  ]
}
